{
  "updated": "2026-04-24T22:43:47.975Z",
  "count": 40,
  "events": [
    {
      "id": "8f1dac3b6ac6c37f7caab4ef94051afc",
      "type": "leadership_change",
      "headline": "EU huddle in Cyprus faces 42.7 question: Mutual defence clause in focus as Trump unsettles Nato",
      "country": "IND",
      "target": "USA",
      "timestamp": "2026-04-24 10:42:55",
      "severity": "medium"
    },
    {
      "id": "da1fa2209aea36a3875850e99f720100",
      "type": "leadership_change",
      "headline": "Former NATO envoy warns of ‘very big mistakes’ in criticizing Trump on Iran",
      "country": "FRA",
      "target": "IRN",
      "timestamp": "2026-04-24 10:41:46",
      "severity": "critical"
    },
    {
      "id": "413378c16bd4cb148de26ca0b8aeb999",
      "type": "military_mobilisation",
      "headline": "Iran 'trapped in slogans' as nuclear talks with US stall after naval standoff, former diplomat says",
      "country": "FRA",
      "target": "IRN",
      "timestamp": "2026-04-24 10:41:25",
      "severity": "critical"
    },
    {
      "id": "57bcc70c8888cec411bf0a4bce29dcab",
      "type": "diplomacy",
      "headline": "How to nominate a truly conservative justice",
      "country": "USA",
      "target": null,
      "timestamp": "2026-04-24 10:41:00",
      "severity": "medium"
    },
    {
      "id": "3ff3508599d0b5322b60e8f08492956f",
      "type": "diplomacy",
      "headline": "EU leaders split on borrowing as MFF talks opened in Nicosia summit",
      "country": "CYP",
      "target": "DEU",
      "timestamp": "2026-04-24 10:40:44",
      "severity": "high"
    },
    {
      "id": "bc440e71afd82d8a3d5416b981014988",
      "type": "military_mobilisation",
      "headline": "Ex-CIA director skewers Trump's 'unforced errors': 'Didn’t have to dig the hole this deep'",
      "country": "UKR",
      "target": "USA",
      "timestamp": "2026-04-24 10:40:11",
      "severity": "critical"
    },
    {
      "id": "79de8c7f00f426ce9ec51023f42adc41",
      "type": "military_mobilisation",
      "headline": "10 Indian nationals died fighting Ukraine war for Russia, Centre tells SC",
      "country": "GBR",
      "target": "UKR",
      "timestamp": "2026-04-24 10:40:00",
      "severity": "critical"
    },
    {
      "id": "edd70ebd096ac18b1ed256c2092ce76b",
      "type": "diplomacy",
      "headline": "Türkiye, Britain sign strategic pact to deepen alliance",
      "country": "TUR",
      "target": "GBR",
      "timestamp": "2026-04-24 10:40:00",
      "severity": "medium"
    },
    {
      "id": "6c22472e41f6cc6fea13f053ee42994c",
      "type": "diplomacy",
      "headline": "Sleeper cells exposed; media experts warn of 'internal war' in Gulf at Dubai forum",
      "country": "ARE",
      "target": "IRN",
      "timestamp": "2026-04-24 10:39:20",
      "severity": "critical"
    },
    {
      "id": "6ad275d8e868bf9bbe858c34a6164a61",
      "type": "military_mobilisation",
      "headline": "Iran shows no urgency for deal as war strategy tests Trump administration",
      "country": "IND",
      "target": "IRN",
      "timestamp": "2026-04-24 10:39:11",
      "severity": "critical"
    },
    {
      "type": "invasion",
      "country": "RUS",
      "target": "UKR",
      "severity": "critical",
      "headline": "Ongoing Russia–Ukraine armed conflict",
      "id": "known-0",
      "timestamp": "2026-04-24T22:43:47.975Z"
    },
    {
      "type": "military_mobilisation",
      "country": "ISR",
      "target": "PSE",
      "severity": "critical",
      "headline": "Israel–Palestine military operations in Gaza",
      "id": "known-1",
      "timestamp": "2026-04-24T22:43:47.975Z"
    },
    {
      "type": "military_mobilisation",
      "country": "ISR",
      "target": "LBN",
      "severity": "high",
      "headline": "Israel–Hezbollah cross-border conflict in Lebanon",
      "id": "known-2",
      "timestamp": "2026-04-24T22:43:47.975Z"
    },
    {
      "type": "military_mobilisation",
      "country": "ISR",
      "target": "SYR",
      "severity": "high",
      "headline": "Israeli military strikes on targets in Syria",
      "id": "known-3",
      "timestamp": "2026-04-24T22:43:47.975Z"
    },
    {
      "type": "military_mobilisation",
      "country": "ISR",
      "target": "YEM",
      "severity": "high",
      "headline": "Israel–Houthi exchange of strikes via Yemen",
      "id": "known-4",
      "timestamp": "2026-04-24T22:43:47.975Z"
    },
    {
      "type": "military_mobilisation",
      "country": "IRN",
      "target": "ISR",
      "severity": "high",
      "headline": "Iran–Israel strategic military confrontation",
      "id": "known-5",
      "timestamp": "2026-04-24T22:43:47.975Z"
    },
    {
      "type": "military_mobilisation",
      "country": "USA",
      "target": "IRN",
      "severity": "high",
      "headline": "US military operations and sanctions against Iran",
      "id": "known-6",
      "timestamp": "2026-04-24T22:43:47.975Z"
    },
    {
      "type": "military_mobilisation",
      "country": "USA",
      "target": "YEM",
      "severity": "high",
      "headline": "US airstrikes on Houthi positions in Yemen",
      "id": "known-7",
      "timestamp": "2026-04-24T22:43:47.975Z"
    },
    {
      "type": "invasion",
      "country": "SDN",
      "target": "SSD",
      "severity": "critical",
      "headline": "Sudan civil war — RSF vs SAF armed conflict",
      "id": "known-8",
      "timestamp": "2026-04-24T22:43:47.975Z"
    },
    {
      "type": "invasion",
      "country": "MMR",
      "target": "MMR",
      "severity": "critical",
      "headline": "Myanmar civil war — junta vs resistance forces",
      "id": "known-9",
      "timestamp": "2026-04-24T22:43:47.975Z"
    },
    {
      "type": "military_mobilisation",
      "country": "ETH",
      "target": "ERI",
      "severity": "high",
      "headline": "Ethiopia–Eritrea border tensions persist",
      "id": "known-10",
      "timestamp": "2026-04-24T22:43:47.975Z"
    },
    {
      "type": "military_mobilisation",
      "country": "SOM",
      "target": "ETH",
      "severity": "high",
      "headline": "Somalia–Ethiopia tensions over Somaliland port deal",
      "id": "known-11",
      "timestamp": "2026-04-24T22:43:47.975Z"
    },
    {
      "type": "military_mobilisation",
      "country": "COD",
      "target": "RWA",
      "severity": "high",
      "headline": "DR Congo–Rwanda conflict over M23 militia in eastern DRC",
      "id": "known-12",
      "timestamp": "2026-04-24T22:43:47.975Z"
    },
    {
      "type": "military_mobilisation",
      "country": "PAK",
      "target": "AFG",
      "severity": "medium",
      "headline": "Pakistan–Afghanistan cross-border military operations",
      "id": "known-13",
      "timestamp": "2026-04-24T22:43:47.975Z"
    },
    {
      "type": "military_mobilisation",
      "country": "CHN",
      "target": "TWN",
      "severity": "high",
      "headline": "China–Taiwan strait military posturing",
      "id": "known-14",
      "timestamp": "2026-04-24T22:43:47.975Z"
    },
    {
      "type": "military_mobilisation",
      "country": "CHN",
      "target": "PHL",
      "severity": "medium",
      "headline": "China–Philippines South China Sea territorial disputes",
      "id": "known-15",
      "timestamp": "2026-04-24T22:43:47.975Z"
    },
    {
      "type": "military_mobilisation",
      "country": "PRK",
      "target": "KOR",
      "severity": "medium",
      "headline": "North Korea–South Korea military standoff",
      "id": "known-16",
      "timestamp": "2026-04-24T22:43:47.975Z"
    },
    {
      "type": "military_mobilisation",
      "country": "IND",
      "target": "PAK",
      "severity": "medium",
      "headline": "India–Pakistan border tensions in Kashmir",
      "id": "known-17",
      "timestamp": "2026-04-24T22:43:47.975Z"
    },
    {
      "type": "military_mobilisation",
      "country": "RUS",
      "target": "GEO",
      "severity": "medium",
      "headline": "Russia–Georgia tensions over occupied territories",
      "id": "known-18",
      "timestamp": "2026-04-24T22:43:47.975Z"
    },
    {
      "type": "trade",
      "country": "CHN",
      "target": "USA",
      "severity": "medium",
      "headline": "US–China trade war and tariff escalation",
      "id": "known-19",
      "timestamp": "2026-04-24T22:43:47.975Z"
    },
    {
      "type": "trade",
      "country": "USA",
      "target": "RUS",
      "severity": "medium",
      "headline": "US-led economic sanctions on Russia",
      "id": "known-20",
      "timestamp": "2026-04-24T22:43:47.975Z"
    },
    {
      "type": "trade",
      "country": "DEU",
      "target": "NOR",
      "severity": "low",
      "headline": "Germany–Norway energy corridor partnership",
      "id": "known-21",
      "timestamp": "2026-04-24T22:43:47.975Z"
    },
    {
      "type": "trade",
      "country": "JPN",
      "target": "USA",
      "severity": "low",
      "headline": "Japan–US semiconductor supply chain agreement",
      "id": "known-22",
      "timestamp": "2026-04-24T22:43:47.975Z"
    },
    {
      "type": "trade",
      "country": "IND",
      "target": "RUS",
      "severity": "medium",
      "headline": "India–Russia oil and energy trade partnership",
      "id": "known-23",
      "timestamp": "2026-04-24T22:43:47.975Z"
    },
    {
      "type": "trade",
      "country": "AUS",
      "target": "CHN",
      "severity": "medium",
      "headline": "Australia–China trade disputes over critical minerals",
      "id": "known-24",
      "timestamp": "2026-04-24T22:43:47.975Z"
    },
    {
      "type": "trade",
      "country": "GBR",
      "target": "FRA",
      "severity": "low",
      "headline": "UK–EU post-Brexit trade friction",
      "id": "known-25",
      "timestamp": "2026-04-24T22:43:47.975Z"
    },
    {
      "type": "trade",
      "country": "KOR",
      "target": "JPN",
      "severity": "low",
      "headline": "South Korea–Japan semiconductor export controls",
      "id": "known-26",
      "timestamp": "2026-04-24T22:43:47.975Z"
    },
    {
      "type": "trade",
      "country": "BRA",
      "target": "CHN",
      "severity": "low",
      "headline": "Brazil–China commodity export corridor",
      "id": "known-27",
      "timestamp": "2026-04-24T22:43:47.975Z"
    },
    {
      "type": "trade",
      "country": "SAU",
      "target": "IND",
      "severity": "low",
      "headline": "Saudi Arabia–India oil supply agreement",
      "id": "known-28",
      "timestamp": "2026-04-24T22:43:47.975Z"
    },
    {
      "type": "trade",
      "country": "TUR",
      "target": "RUS",
      "severity": "medium",
      "headline": "Turkey–Russia energy and trade corridor",
      "id": "known-29",
      "timestamp": "2026-04-24T22:43:47.975Z"
    }
  ]
}