{
  "updated": "2026-07-13T00:49:14.194Z",
  "count": 37,
  "events": [
    {
      "id": "4029e2af13cd97275ea17b11115efa5e",
      "type": "diplomacy",
      "headline": "Lower House begins extraordinary session, reviews five reform-oriented draft laws",
      "country": "JOR",
      "target": "USA",
      "timestamp": "2026-07-12 12:48:37",
      "severity": "medium"
    },
    {
      "id": "18e1ef7a7094cefbac4a947f10fedd2d",
      "type": "leadership_change",
      "headline": "Trump praises Lindsey Graham as ‘one of the greatest people I have ever known’ after senator dies of sudden illness – live",
      "country": "USA",
      "target": null,
      "timestamp": "2026-07-12 12:48:23",
      "severity": "medium"
    },
    {
      "id": "6e534535cfcc7d9f92c2c3cf0c6667cf",
      "type": "diplomacy",
      "headline": "Between the Seriousness of Sport and the Absurdity of Politics",
      "country": "ARE",
      "target": "USA",
      "timestamp": "2026-07-12 12:48:19",
      "severity": "medium"
    },
    {
      "id": "6c6dd26c1a0987cc439e9f86725e98e7",
      "type": "leadership_change",
      "headline": "“Leave Tinubu Alone!” Prophet Odumeje Fiercely Attacks Pastor Adeboye Just Weeks After RCCG Leader Endorses President Tinubu",
      "country": "NGA",
      "target": "NER",
      "timestamp": "2026-07-12 12:48:01",
      "severity": "critical"
    },
    {
      "id": "2c363fe4cdf4d1ef7c01c530f3551137",
      "type": "diplomacy",
      "headline": "How a Pakistani Woman And Her Son Hide Their Nationality To Secure Ration, Voter Cards In Karnataka",
      "country": "IND",
      "target": "PAK",
      "timestamp": "2026-07-12 12:47:49",
      "severity": "medium"
    },
    {
      "id": "74185363c1c41f0ef9ad07e9562c2e26",
      "type": "leadership_change",
      "headline": "Prime Minister Of Iraq To Visit Washington On Monday",
      "country": "IND",
      "target": "USA",
      "timestamp": "2026-07-12 12:47:42",
      "severity": "medium"
    },
    {
      "id": "692f1043a6b92fba80562a52e3d35fe9",
      "type": "military_mobilisation",
      "headline": "Army Chief, Colorado Adjutant General discuss cooperation",
      "country": "JOR",
      "target": "USA",
      "timestamp": "2026-07-12 12:47:12",
      "severity": "low"
    },
    {
      "id": "5ac59eba5a4647d20912c58be028fde7",
      "type": "diplomacy",
      "headline": "Lindsey Graham death updates: Trump and others pay tribute after Republican South Carolina senator dies aged 71",
      "country": "GBR",
      "target": "USA",
      "timestamp": "2026-07-12 12:46:24",
      "severity": "medium"
    },
    {
      "type": "invasion",
      "country": "RUS",
      "target": "UKR",
      "severity": "critical",
      "headline": "Ongoing Russia–Ukraine armed conflict",
      "id": "known-0",
      "timestamp": "2026-07-13T00:49:14.194Z"
    },
    {
      "type": "military_mobilisation",
      "country": "ISR",
      "target": "PSE",
      "severity": "critical",
      "headline": "Israel–Palestine military operations in Gaza",
      "id": "known-1",
      "timestamp": "2026-07-13T00:49:14.194Z"
    },
    {
      "type": "military_mobilisation",
      "country": "ISR",
      "target": "LBN",
      "severity": "high",
      "headline": "Israel–Hezbollah cross-border conflict in Lebanon",
      "id": "known-2",
      "timestamp": "2026-07-13T00:49:14.194Z"
    },
    {
      "type": "military_mobilisation",
      "country": "ISR",
      "target": "SYR",
      "severity": "high",
      "headline": "Israeli military strikes on targets in Syria",
      "id": "known-3",
      "timestamp": "2026-07-13T00:49:14.194Z"
    },
    {
      "type": "military_mobilisation",
      "country": "ISR",
      "target": "YEM",
      "severity": "high",
      "headline": "Israel–Houthi exchange of strikes via Yemen",
      "id": "known-4",
      "timestamp": "2026-07-13T00:49:14.194Z"
    },
    {
      "type": "military_mobilisation",
      "country": "IRN",
      "target": "ISR",
      "severity": "high",
      "headline": "Iran–Israel strategic military confrontation",
      "id": "known-5",
      "timestamp": "2026-07-13T00:49:14.194Z"
    },
    {
      "type": "military_mobilisation",
      "country": "USA",
      "target": "IRN",
      "severity": "high",
      "headline": "US military operations and sanctions against Iran",
      "id": "known-6",
      "timestamp": "2026-07-13T00:49:14.194Z"
    },
    {
      "type": "military_mobilisation",
      "country": "USA",
      "target": "YEM",
      "severity": "high",
      "headline": "US airstrikes on Houthi positions in Yemen",
      "id": "known-7",
      "timestamp": "2026-07-13T00:49:14.194Z"
    },
    {
      "type": "invasion",
      "country": "SDN",
      "target": "SSD",
      "severity": "critical",
      "headline": "Sudan civil war — RSF vs SAF armed conflict",
      "id": "known-8",
      "timestamp": "2026-07-13T00:49:14.194Z"
    },
    {
      "type": "invasion",
      "country": "MMR",
      "target": "MMR",
      "severity": "critical",
      "headline": "Myanmar civil war — junta vs resistance forces",
      "id": "known-9",
      "timestamp": "2026-07-13T00:49:14.194Z"
    },
    {
      "type": "military_mobilisation",
      "country": "ETH",
      "target": "ERI",
      "severity": "high",
      "headline": "Ethiopia–Eritrea border tensions persist",
      "id": "known-10",
      "timestamp": "2026-07-13T00:49:14.194Z"
    },
    {
      "type": "military_mobilisation",
      "country": "SOM",
      "target": "ETH",
      "severity": "high",
      "headline": "Somalia–Ethiopia tensions over Somaliland port deal",
      "id": "known-11",
      "timestamp": "2026-07-13T00:49:14.194Z"
    },
    {
      "type": "military_mobilisation",
      "country": "COD",
      "target": "RWA",
      "severity": "high",
      "headline": "DR Congo–Rwanda conflict over M23 militia in eastern DRC",
      "id": "known-12",
      "timestamp": "2026-07-13T00:49:14.194Z"
    },
    {
      "type": "military_mobilisation",
      "country": "PAK",
      "target": "AFG",
      "severity": "medium",
      "headline": "Pakistan–Afghanistan cross-border military operations",
      "id": "known-13",
      "timestamp": "2026-07-13T00:49:14.194Z"
    },
    {
      "type": "military_mobilisation",
      "country": "CHN",
      "target": "TWN",
      "severity": "high",
      "headline": "China–Taiwan strait military posturing",
      "id": "known-14",
      "timestamp": "2026-07-13T00:49:14.194Z"
    },
    {
      "type": "military_mobilisation",
      "country": "CHN",
      "target": "PHL",
      "severity": "medium",
      "headline": "China–Philippines South China Sea territorial disputes",
      "id": "known-15",
      "timestamp": "2026-07-13T00:49:14.194Z"
    },
    {
      "type": "military_mobilisation",
      "country": "PRK",
      "target": "KOR",
      "severity": "medium",
      "headline": "North Korea–South Korea military standoff",
      "id": "known-16",
      "timestamp": "2026-07-13T00:49:14.194Z"
    },
    {
      "type": "military_mobilisation",
      "country": "RUS",
      "target": "GEO",
      "severity": "medium",
      "headline": "Russia–Georgia tensions over occupied territories",
      "id": "known-17",
      "timestamp": "2026-07-13T00:49:14.194Z"
    },
    {
      "type": "trade",
      "country": "CHN",
      "target": "USA",
      "severity": "medium",
      "headline": "US–China trade war and tariff escalation",
      "id": "known-18",
      "timestamp": "2026-07-13T00:49:14.194Z"
    },
    {
      "type": "trade",
      "country": "USA",
      "target": "RUS",
      "severity": "medium",
      "headline": "US-led economic sanctions on Russia",
      "id": "known-19",
      "timestamp": "2026-07-13T00:49:14.194Z"
    },
    {
      "type": "trade",
      "country": "DEU",
      "target": "NOR",
      "severity": "low",
      "headline": "Germany–Norway energy corridor partnership",
      "id": "known-20",
      "timestamp": "2026-07-13T00:49:14.194Z"
    },
    {
      "type": "trade",
      "country": "JPN",
      "target": "USA",
      "severity": "low",
      "headline": "Japan–US semiconductor supply chain agreement",
      "id": "known-21",
      "timestamp": "2026-07-13T00:49:14.194Z"
    },
    {
      "type": "trade",
      "country": "IND",
      "target": "RUS",
      "severity": "medium",
      "headline": "India–Russia oil and energy trade partnership",
      "id": "known-22",
      "timestamp": "2026-07-13T00:49:14.194Z"
    },
    {
      "type": "trade",
      "country": "AUS",
      "target": "CHN",
      "severity": "medium",
      "headline": "Australia–China trade disputes over critical minerals",
      "id": "known-23",
      "timestamp": "2026-07-13T00:49:14.194Z"
    },
    {
      "type": "trade",
      "country": "GBR",
      "target": "FRA",
      "severity": "low",
      "headline": "UK–EU post-Brexit trade friction",
      "id": "known-24",
      "timestamp": "2026-07-13T00:49:14.194Z"
    },
    {
      "type": "trade",
      "country": "KOR",
      "target": "JPN",
      "severity": "low",
      "headline": "South Korea–Japan semiconductor export controls",
      "id": "known-25",
      "timestamp": "2026-07-13T00:49:14.194Z"
    },
    {
      "type": "trade",
      "country": "BRA",
      "target": "CHN",
      "severity": "low",
      "headline": "Brazil–China commodity export corridor",
      "id": "known-26",
      "timestamp": "2026-07-13T00:49:14.194Z"
    },
    {
      "type": "trade",
      "country": "SAU",
      "target": "IND",
      "severity": "low",
      "headline": "Saudi Arabia–India oil supply agreement",
      "id": "known-27",
      "timestamp": "2026-07-13T00:49:14.194Z"
    },
    {
      "type": "trade",
      "country": "TUR",
      "target": "RUS",
      "severity": "medium",
      "headline": "Turkey–Russia energy and trade corridor",
      "id": "known-28",
      "timestamp": "2026-07-13T00:49:14.194Z"
    }
  ]
}