{
  "updated": "2026-03-23T19:26:02.944Z",
  "count": 40,
  "events": [
    {
      "id": "6ceb5c1de155851180cd24aad1da0c4e",
      "type": "leadership_change",
      "headline": "Marcos orders creation of crisis committee",
      "country": "PHL",
      "target": null,
      "timestamp": "2026-03-23 07:26:00",
      "severity": "high"
    },
    {
      "id": "9d4afffc6a9786619110f6a775bff8d3",
      "type": "military_mobilisation",
      "headline": "Iran Strikes Near Israel’s Dimona Nuclear Hub, Global Nuclear War Fears Rise",
      "country": "IND",
      "target": "ISR",
      "timestamp": "2026-03-23 07:26:00",
      "severity": "critical"
    },
    {
      "id": "d83e9fcc0a6f7f4b1473f2574b9fe2d5",
      "type": "diplomacy",
      "headline": "United States issues global warning",
      "country": "ZAF",
      "target": "USA",
      "timestamp": "2026-03-23 07:25:16",
      "severity": "critical"
    },
    {
      "id": "826231cbe7db5d394d75c03270862b05",
      "type": "military_mobilisation",
      "headline": "How the EU forced Starmer’s hand on the British bases in Cyprus",
      "country": "CYP",
      "target": "USA",
      "timestamp": "2026-03-23 07:25:06",
      "severity": "high"
    },
    {
      "id": "b584d8f093b5d3fa4bf0f730bd302b62",
      "type": "invasion",
      "headline": "Coast Guard denies foreign yacht entry to Akureyri",
      "country": "ISL",
      "target": "UKR",
      "timestamp": "2026-03-23 07:25:04",
      "severity": "critical"
    },
    {
      "id": "bcef29236090de25687ee6fb331dd4a4",
      "type": "leadership_change",
      "headline": "First Deputy PM stresses heightened vigilance during inspection tour of border security units",
      "country": "KWT",
      "target": "USA",
      "timestamp": "2026-03-23 07:25:00",
      "severity": "medium"
    },
    {
      "id": "585ee0327783e9fc930b60884fb7541f",
      "type": "military_mobilisation",
      "headline": "Russians attack Kryvyi Rih again; two people wounded",
      "country": "UKR",
      "target": "RUS",
      "timestamp": "2026-03-23 07:25:00",
      "severity": "critical"
    },
    {
      "id": "e1d4f269fa6b8fac97a31fa9304fe920",
      "type": "diplomacy",
      "headline": "World News | EAM Jaishankar Speaks with German FM Wadephul on West Asia Conflict",
      "country": "IND",
      "target": "USA",
      "timestamp": "2026-03-23 07:24:18",
      "severity": "medium"
    },
    {
      "id": "f4f17446970199524324f881e3f0ec0d",
      "type": "diplomacy",
      "headline": "Parliament Budget Session 2026 Live Updates: PM Modi To Speak On Middle East Conflict At 2 PM",
      "country": "IND",
      "target": null,
      "timestamp": "2026-03-23 07:24:04",
      "severity": "medium"
    },
    {
      "id": "c7837fc6e4faed6b347a1c7365a38eaf",
      "type": "military_mobilisation",
      "headline": "Civilian rights violations reported amid TNLA–MNDAA dispute",
      "country": "MMR",
      "target": null,
      "timestamp": "2026-03-23 07:24:00",
      "severity": "medium"
    },
    {
      "type": "invasion",
      "country": "RUS",
      "target": "UKR",
      "severity": "critical",
      "headline": "Ongoing Russia–Ukraine armed conflict",
      "id": "known-0",
      "timestamp": "2026-03-23T19:26:02.943Z"
    },
    {
      "type": "military_mobilisation",
      "country": "ISR",
      "target": "PSE",
      "severity": "critical",
      "headline": "Israel–Palestine military operations in Gaza",
      "id": "known-1",
      "timestamp": "2026-03-23T19:26:02.943Z"
    },
    {
      "type": "military_mobilisation",
      "country": "ISR",
      "target": "LBN",
      "severity": "high",
      "headline": "Israel–Hezbollah cross-border conflict in Lebanon",
      "id": "known-2",
      "timestamp": "2026-03-23T19:26:02.943Z"
    },
    {
      "type": "military_mobilisation",
      "country": "ISR",
      "target": "SYR",
      "severity": "high",
      "headline": "Israeli military strikes on targets in Syria",
      "id": "known-3",
      "timestamp": "2026-03-23T19:26:02.943Z"
    },
    {
      "type": "military_mobilisation",
      "country": "ISR",
      "target": "YEM",
      "severity": "high",
      "headline": "Israel–Houthi exchange of strikes via Yemen",
      "id": "known-4",
      "timestamp": "2026-03-23T19:26:02.943Z"
    },
    {
      "type": "military_mobilisation",
      "country": "IRN",
      "target": "ISR",
      "severity": "high",
      "headline": "Iran–Israel strategic military confrontation",
      "id": "known-5",
      "timestamp": "2026-03-23T19:26:02.943Z"
    },
    {
      "type": "military_mobilisation",
      "country": "USA",
      "target": "IRN",
      "severity": "high",
      "headline": "US military operations and sanctions against Iran",
      "id": "known-6",
      "timestamp": "2026-03-23T19:26:02.943Z"
    },
    {
      "type": "military_mobilisation",
      "country": "USA",
      "target": "YEM",
      "severity": "high",
      "headline": "US airstrikes on Houthi positions in Yemen",
      "id": "known-7",
      "timestamp": "2026-03-23T19:26:02.943Z"
    },
    {
      "type": "invasion",
      "country": "SDN",
      "target": "SSD",
      "severity": "critical",
      "headline": "Sudan civil war — RSF vs SAF armed conflict",
      "id": "known-8",
      "timestamp": "2026-03-23T19:26:02.943Z"
    },
    {
      "type": "invasion",
      "country": "MMR",
      "target": "MMR",
      "severity": "critical",
      "headline": "Myanmar civil war — junta vs resistance forces",
      "id": "known-9",
      "timestamp": "2026-03-23T19:26:02.943Z"
    },
    {
      "type": "military_mobilisation",
      "country": "ETH",
      "target": "ERI",
      "severity": "high",
      "headline": "Ethiopia–Eritrea border tensions persist",
      "id": "known-10",
      "timestamp": "2026-03-23T19:26:02.943Z"
    },
    {
      "type": "military_mobilisation",
      "country": "SOM",
      "target": "ETH",
      "severity": "high",
      "headline": "Somalia–Ethiopia tensions over Somaliland port deal",
      "id": "known-11",
      "timestamp": "2026-03-23T19:26:02.943Z"
    },
    {
      "type": "military_mobilisation",
      "country": "COD",
      "target": "RWA",
      "severity": "high",
      "headline": "DR Congo–Rwanda conflict over M23 militia in eastern DRC",
      "id": "known-12",
      "timestamp": "2026-03-23T19:26:02.943Z"
    },
    {
      "type": "military_mobilisation",
      "country": "PAK",
      "target": "AFG",
      "severity": "medium",
      "headline": "Pakistan–Afghanistan cross-border military operations",
      "id": "known-13",
      "timestamp": "2026-03-23T19:26:02.943Z"
    },
    {
      "type": "military_mobilisation",
      "country": "CHN",
      "target": "TWN",
      "severity": "high",
      "headline": "China–Taiwan strait military posturing",
      "id": "known-14",
      "timestamp": "2026-03-23T19:26:02.943Z"
    },
    {
      "type": "military_mobilisation",
      "country": "CHN",
      "target": "PHL",
      "severity": "medium",
      "headline": "China–Philippines South China Sea territorial disputes",
      "id": "known-15",
      "timestamp": "2026-03-23T19:26:02.943Z"
    },
    {
      "type": "military_mobilisation",
      "country": "PRK",
      "target": "KOR",
      "severity": "medium",
      "headline": "North Korea–South Korea military standoff",
      "id": "known-16",
      "timestamp": "2026-03-23T19:26:02.943Z"
    },
    {
      "type": "military_mobilisation",
      "country": "IND",
      "target": "PAK",
      "severity": "medium",
      "headline": "India–Pakistan border tensions in Kashmir",
      "id": "known-17",
      "timestamp": "2026-03-23T19:26:02.943Z"
    },
    {
      "type": "military_mobilisation",
      "country": "RUS",
      "target": "GEO",
      "severity": "medium",
      "headline": "Russia–Georgia tensions over occupied territories",
      "id": "known-18",
      "timestamp": "2026-03-23T19:26:02.943Z"
    },
    {
      "type": "trade",
      "country": "CHN",
      "target": "USA",
      "severity": "medium",
      "headline": "US–China trade war and tariff escalation",
      "id": "known-19",
      "timestamp": "2026-03-23T19:26:02.943Z"
    },
    {
      "type": "trade",
      "country": "USA",
      "target": "RUS",
      "severity": "medium",
      "headline": "US-led economic sanctions on Russia",
      "id": "known-20",
      "timestamp": "2026-03-23T19:26:02.943Z"
    },
    {
      "type": "trade",
      "country": "DEU",
      "target": "NOR",
      "severity": "low",
      "headline": "Germany–Norway energy corridor partnership",
      "id": "known-21",
      "timestamp": "2026-03-23T19:26:02.943Z"
    },
    {
      "type": "trade",
      "country": "JPN",
      "target": "USA",
      "severity": "low",
      "headline": "Japan–US semiconductor supply chain agreement",
      "id": "known-22",
      "timestamp": "2026-03-23T19:26:02.943Z"
    },
    {
      "type": "trade",
      "country": "IND",
      "target": "RUS",
      "severity": "medium",
      "headline": "India–Russia oil and energy trade partnership",
      "id": "known-23",
      "timestamp": "2026-03-23T19:26:02.943Z"
    },
    {
      "type": "trade",
      "country": "AUS",
      "target": "CHN",
      "severity": "medium",
      "headline": "Australia–China trade disputes over critical minerals",
      "id": "known-24",
      "timestamp": "2026-03-23T19:26:02.943Z"
    },
    {
      "type": "trade",
      "country": "GBR",
      "target": "FRA",
      "severity": "low",
      "headline": "UK–EU post-Brexit trade friction",
      "id": "known-25",
      "timestamp": "2026-03-23T19:26:02.943Z"
    },
    {
      "type": "trade",
      "country": "KOR",
      "target": "JPN",
      "severity": "low",
      "headline": "South Korea–Japan semiconductor export controls",
      "id": "known-26",
      "timestamp": "2026-03-23T19:26:02.943Z"
    },
    {
      "type": "trade",
      "country": "BRA",
      "target": "CHN",
      "severity": "low",
      "headline": "Brazil–China commodity export corridor",
      "id": "known-27",
      "timestamp": "2026-03-23T19:26:02.943Z"
    },
    {
      "type": "trade",
      "country": "SAU",
      "target": "IND",
      "severity": "low",
      "headline": "Saudi Arabia–India oil supply agreement",
      "id": "known-28",
      "timestamp": "2026-03-23T19:26:02.943Z"
    },
    {
      "type": "trade",
      "country": "TUR",
      "target": "RUS",
      "severity": "medium",
      "headline": "Turkey–Russia energy and trade corridor",
      "id": "known-29",
      "timestamp": "2026-03-23T19:26:02.944Z"
    }
  ]
}