{
  "updated": "2026-03-07T23:18:50.057Z",
  "count": 39,
  "events": [
    {
      "id": "b607e408e4a2dc6374013065cff7d93f",
      "type": "military_mobilisation",
      "headline": "Patriarch Sako: ‘War is not the solution’",
      "country": "USA",
      "target": "ISR",
      "timestamp": "2026-03-07 11:18:00",
      "severity": "critical"
    },
    {
      "id": "b39cd03a852153ea0215bf0a40047ad1",
      "type": "trade",
      "headline": "Pakistan's food crisis deepens as Iran war rattles supply chains",
      "country": "PAK",
      "target": "ISR",
      "timestamp": "2026-03-07 11:17:59",
      "severity": "critical"
    },
    {
      "id": "4f35b41d43d69fea348c86f9912a4c44",
      "type": "leadership_change",
      "headline": "Iran’s President rules out ‘surrender’, says neighbouring countries won’t be targeted",
      "country": "IND",
      "target": "ISR",
      "timestamp": "2026-03-07 11:17:37",
      "severity": "critical"
    },
    {
      "id": "c64c1e4d7af045db96cfdff47e981383",
      "type": "diplomacy",
      "headline": "Govt launches hotline to support expatriates facing visa, flight issues",
      "country": "BGD",
      "target": "USA",
      "timestamp": "2026-03-07 11:17:35",
      "severity": "medium"
    },
    {
      "id": "23eeb8fcb4d56ecaed31358d9b0a4b8e",
      "type": "leadership_change",
      "headline": "IRGC says neighbors’ sovereignty respected, warns of strikes on US-Israel bases",
      "country": "BGD",
      "target": "ISR",
      "timestamp": "2026-03-07 11:17:34",
      "severity": "critical"
    },
    {
      "id": "4c35db917847713be305a0d7cf777492",
      "type": "diplomacy",
      "headline": "You donâ€TMt have to like Iranâ€TMs government to oppose this war",
      "country": "IRN",
      "target": "USA",
      "timestamp": "2026-03-07 11:17:34",
      "severity": "critical"
    },
    {
      "id": "84aabe427d4ca13c066580e77475af1b",
      "type": "military_mobilisation",
      "headline": "Is Iran Running Out Of Missiles? Arsenal Shrinks By 90% As Israel-US Strikes Intensify, From 3,000 To... How Many Weapons Are Left With Tehran?",
      "country": "IND",
      "target": "USA",
      "timestamp": "2026-03-07 11:17:22",
      "severity": "critical"
    },
    {
      "id": "e7c640343538070b7f4db21b1ea0c438",
      "type": "leadership_change",
      "headline": "Iran says will not target neighbours unless attacked from them | International",
      "country": "BGD",
      "target": "IRN",
      "timestamp": "2026-03-07 11:17:00",
      "severity": "critical"
    },
    {
      "id": "e7fd8f43e260f376186c141c4d132d9a",
      "type": "diplomacy",
      "headline": "WI team stranded in Kolkata as US-Israeli air strike on Iran curbs disrupt travel post T20 world cup exit",
      "country": "IND",
      "target": "ZAF",
      "timestamp": "2026-03-07 11:16:38",
      "severity": "medium"
    },
    {
      "type": "invasion",
      "country": "RUS",
      "target": "UKR",
      "severity": "critical",
      "headline": "Ongoing Russia–Ukraine armed conflict",
      "id": "known-0",
      "timestamp": "2026-03-07T23:18:50.056Z"
    },
    {
      "type": "military_mobilisation",
      "country": "ISR",
      "target": "PSE",
      "severity": "critical",
      "headline": "Israel–Palestine military operations in Gaza",
      "id": "known-1",
      "timestamp": "2026-03-07T23:18:50.056Z"
    },
    {
      "type": "military_mobilisation",
      "country": "ISR",
      "target": "LBN",
      "severity": "high",
      "headline": "Israel–Hezbollah cross-border conflict in Lebanon",
      "id": "known-2",
      "timestamp": "2026-03-07T23:18:50.056Z"
    },
    {
      "type": "military_mobilisation",
      "country": "ISR",
      "target": "SYR",
      "severity": "high",
      "headline": "Israeli military strikes on targets in Syria",
      "id": "known-3",
      "timestamp": "2026-03-07T23:18:50.056Z"
    },
    {
      "type": "military_mobilisation",
      "country": "ISR",
      "target": "YEM",
      "severity": "high",
      "headline": "Israel–Houthi exchange of strikes via Yemen",
      "id": "known-4",
      "timestamp": "2026-03-07T23:18:50.056Z"
    },
    {
      "type": "military_mobilisation",
      "country": "IRN",
      "target": "ISR",
      "severity": "high",
      "headline": "Iran–Israel strategic military confrontation",
      "id": "known-5",
      "timestamp": "2026-03-07T23:18:50.056Z"
    },
    {
      "type": "military_mobilisation",
      "country": "USA",
      "target": "IRN",
      "severity": "high",
      "headline": "US military operations and sanctions against Iran",
      "id": "known-6",
      "timestamp": "2026-03-07T23:18:50.056Z"
    },
    {
      "type": "military_mobilisation",
      "country": "USA",
      "target": "YEM",
      "severity": "high",
      "headline": "US airstrikes on Houthi positions in Yemen",
      "id": "known-7",
      "timestamp": "2026-03-07T23:18:50.056Z"
    },
    {
      "type": "invasion",
      "country": "SDN",
      "target": "SSD",
      "severity": "critical",
      "headline": "Sudan civil war — RSF vs SAF armed conflict",
      "id": "known-8",
      "timestamp": "2026-03-07T23:18:50.056Z"
    },
    {
      "type": "invasion",
      "country": "MMR",
      "target": "MMR",
      "severity": "critical",
      "headline": "Myanmar civil war — junta vs resistance forces",
      "id": "known-9",
      "timestamp": "2026-03-07T23:18:50.056Z"
    },
    {
      "type": "military_mobilisation",
      "country": "ETH",
      "target": "ERI",
      "severity": "high",
      "headline": "Ethiopia–Eritrea border tensions persist",
      "id": "known-10",
      "timestamp": "2026-03-07T23:18:50.056Z"
    },
    {
      "type": "military_mobilisation",
      "country": "SOM",
      "target": "ETH",
      "severity": "high",
      "headline": "Somalia–Ethiopia tensions over Somaliland port deal",
      "id": "known-11",
      "timestamp": "2026-03-07T23:18:50.056Z"
    },
    {
      "type": "military_mobilisation",
      "country": "COD",
      "target": "RWA",
      "severity": "high",
      "headline": "DR Congo–Rwanda conflict over M23 militia in eastern DRC",
      "id": "known-12",
      "timestamp": "2026-03-07T23:18:50.056Z"
    },
    {
      "type": "military_mobilisation",
      "country": "PAK",
      "target": "AFG",
      "severity": "medium",
      "headline": "Pakistan–Afghanistan cross-border military operations",
      "id": "known-13",
      "timestamp": "2026-03-07T23:18:50.056Z"
    },
    {
      "type": "military_mobilisation",
      "country": "CHN",
      "target": "TWN",
      "severity": "high",
      "headline": "China–Taiwan strait military posturing",
      "id": "known-14",
      "timestamp": "2026-03-07T23:18:50.056Z"
    },
    {
      "type": "military_mobilisation",
      "country": "CHN",
      "target": "PHL",
      "severity": "medium",
      "headline": "China–Philippines South China Sea territorial disputes",
      "id": "known-15",
      "timestamp": "2026-03-07T23:18:50.056Z"
    },
    {
      "type": "military_mobilisation",
      "country": "PRK",
      "target": "KOR",
      "severity": "medium",
      "headline": "North Korea–South Korea military standoff",
      "id": "known-16",
      "timestamp": "2026-03-07T23:18:50.056Z"
    },
    {
      "type": "military_mobilisation",
      "country": "IND",
      "target": "PAK",
      "severity": "medium",
      "headline": "India–Pakistan border tensions in Kashmir",
      "id": "known-17",
      "timestamp": "2026-03-07T23:18:50.056Z"
    },
    {
      "type": "military_mobilisation",
      "country": "RUS",
      "target": "GEO",
      "severity": "medium",
      "headline": "Russia–Georgia tensions over occupied territories",
      "id": "known-18",
      "timestamp": "2026-03-07T23:18:50.056Z"
    },
    {
      "type": "trade",
      "country": "CHN",
      "target": "USA",
      "severity": "medium",
      "headline": "US–China trade war and tariff escalation",
      "id": "known-19",
      "timestamp": "2026-03-07T23:18:50.056Z"
    },
    {
      "type": "trade",
      "country": "USA",
      "target": "RUS",
      "severity": "medium",
      "headline": "US-led economic sanctions on Russia",
      "id": "known-20",
      "timestamp": "2026-03-07T23:18:50.056Z"
    },
    {
      "type": "trade",
      "country": "DEU",
      "target": "NOR",
      "severity": "low",
      "headline": "Germany–Norway energy corridor partnership",
      "id": "known-21",
      "timestamp": "2026-03-07T23:18:50.056Z"
    },
    {
      "type": "trade",
      "country": "JPN",
      "target": "USA",
      "severity": "low",
      "headline": "Japan–US semiconductor supply chain agreement",
      "id": "known-22",
      "timestamp": "2026-03-07T23:18:50.056Z"
    },
    {
      "type": "trade",
      "country": "IND",
      "target": "RUS",
      "severity": "medium",
      "headline": "India–Russia oil and energy trade partnership",
      "id": "known-23",
      "timestamp": "2026-03-07T23:18:50.056Z"
    },
    {
      "type": "trade",
      "country": "AUS",
      "target": "CHN",
      "severity": "medium",
      "headline": "Australia–China trade disputes over critical minerals",
      "id": "known-24",
      "timestamp": "2026-03-07T23:18:50.056Z"
    },
    {
      "type": "trade",
      "country": "GBR",
      "target": "FRA",
      "severity": "low",
      "headline": "UK–EU post-Brexit trade friction",
      "id": "known-25",
      "timestamp": "2026-03-07T23:18:50.056Z"
    },
    {
      "type": "trade",
      "country": "KOR",
      "target": "JPN",
      "severity": "low",
      "headline": "South Korea–Japan semiconductor export controls",
      "id": "known-26",
      "timestamp": "2026-03-07T23:18:50.056Z"
    },
    {
      "type": "trade",
      "country": "BRA",
      "target": "CHN",
      "severity": "low",
      "headline": "Brazil–China commodity export corridor",
      "id": "known-27",
      "timestamp": "2026-03-07T23:18:50.056Z"
    },
    {
      "type": "trade",
      "country": "SAU",
      "target": "IND",
      "severity": "low",
      "headline": "Saudi Arabia–India oil supply agreement",
      "id": "known-28",
      "timestamp": "2026-03-07T23:18:50.056Z"
    },
    {
      "type": "trade",
      "country": "TUR",
      "target": "RUS",
      "severity": "medium",
      "headline": "Turkey–Russia energy and trade corridor",
      "id": "known-29",
      "timestamp": "2026-03-07T23:18:50.056Z"
    }
  ]
}