{
  "updated": "2026-07-18T23:15:55.399Z",
  "count": 37,
  "events": [
    {
      "id": "5939707ddd3fbf2eb6a6e88e5efd02af",
      "type": "diplomacy",
      "headline": "Col. Larry Wilkerson: The world is sleepwalking into potential nuclear war over Iran",
      "country": "GBR",
      "target": "IRN",
      "timestamp": "2026-07-18 11:14:33",
      "severity": "critical"
    },
    {
      "id": "52a1daec14cb3f945164761dd0881f39",
      "type": "military_mobilisation",
      "headline": "Kuwait military intercepts hostile missiles, drones amid Iranian attacks",
      "country": "KWT",
      "target": "IRN",
      "timestamp": "2026-07-18 11:14:00",
      "severity": "critical"
    },
    {
      "id": "3df5c8ca26fafe2103bfd0bec7561f97",
      "type": "military_mobilisation",
      "headline": "Three Palestinians Killed in Israeli Airstrike Targeting Civilians in Gaza",
      "country": "YEM",
      "target": "ISR",
      "timestamp": "2026-07-18 11:13:46",
      "severity": "critical"
    },
    {
      "id": "3cb552f6c74f183d1e4265b99ed391ee",
      "type": "leadership_change",
      "headline": "Israel Plans New Settlements In Gaza And West Bank. Here's What We Know",
      "country": "IND",
      "target": "ISR",
      "timestamp": "2026-07-18 11:13:43",
      "severity": "medium"
    },
    {
      "id": "4a65c01ca8160023d81700bdcc7f164c",
      "type": "trade",
      "headline": "Iraq, Syria sign deal to revive oil pipeline to Mediterranean",
      "country": "IRN",
      "target": "ISR",
      "timestamp": "2026-07-18 11:13:16",
      "severity": "critical"
    },
    {
      "id": "e4f7ec7b74d89aec18a737d792c0488d",
      "type": "military_mobilisation",
      "headline": "IRGC: Destruction of US Forces Gathering Site in Arifjan, Radar at Ali Al Salem Air Base in Kuwait",
      "country": "YEM",
      "target": "KWT",
      "timestamp": "2026-07-18 11:13:12",
      "severity": "high"
    },
    {
      "id": "be4d39dc2a1f498200310b6d0038ea82",
      "type": "military_mobilisation",
      "headline": "Iranian Army Announces Drone Attacks on US Military Bases, Centers in Jordan, Kuwait",
      "country": "YEM",
      "target": "JOR",
      "timestamp": "2026-07-18 11:11:43",
      "severity": "critical"
    },
    {
      "id": "52b29a48b98dc9a5b513c52997fa3031",
      "type": "diplomacy",
      "headline": "Under the hashtag \"They Lied to You\".. A Palestinian digital campaign exposes the falsehood of the truce and documents the continuation of massacres in Gaza",
      "country": "PSE",
      "target": null,
      "timestamp": "2026-07-18 11:11:41",
      "severity": "critical"
    },
    {
      "type": "invasion",
      "country": "RUS",
      "target": "UKR",
      "severity": "critical",
      "headline": "Ongoing Russia–Ukraine armed conflict",
      "id": "known-0",
      "timestamp": "2026-07-18T23:15:55.398Z"
    },
    {
      "type": "military_mobilisation",
      "country": "ISR",
      "target": "PSE",
      "severity": "critical",
      "headline": "Israel–Palestine military operations in Gaza",
      "id": "known-1",
      "timestamp": "2026-07-18T23:15:55.398Z"
    },
    {
      "type": "military_mobilisation",
      "country": "ISR",
      "target": "LBN",
      "severity": "high",
      "headline": "Israel–Hezbollah cross-border conflict in Lebanon",
      "id": "known-2",
      "timestamp": "2026-07-18T23:15:55.398Z"
    },
    {
      "type": "military_mobilisation",
      "country": "ISR",
      "target": "SYR",
      "severity": "high",
      "headline": "Israeli military strikes on targets in Syria",
      "id": "known-3",
      "timestamp": "2026-07-18T23:15:55.398Z"
    },
    {
      "type": "military_mobilisation",
      "country": "ISR",
      "target": "YEM",
      "severity": "high",
      "headline": "Israel–Houthi exchange of strikes via Yemen",
      "id": "known-4",
      "timestamp": "2026-07-18T23:15:55.398Z"
    },
    {
      "type": "military_mobilisation",
      "country": "USA",
      "target": "IRN",
      "severity": "high",
      "headline": "US military operations and sanctions against Iran",
      "id": "known-5",
      "timestamp": "2026-07-18T23:15:55.398Z"
    },
    {
      "type": "military_mobilisation",
      "country": "USA",
      "target": "YEM",
      "severity": "high",
      "headline": "US airstrikes on Houthi positions in Yemen",
      "id": "known-6",
      "timestamp": "2026-07-18T23:15:55.398Z"
    },
    {
      "type": "invasion",
      "country": "SDN",
      "target": "SSD",
      "severity": "critical",
      "headline": "Sudan civil war — RSF vs SAF armed conflict",
      "id": "known-7",
      "timestamp": "2026-07-18T23:15:55.398Z"
    },
    {
      "type": "invasion",
      "country": "MMR",
      "target": "MMR",
      "severity": "critical",
      "headline": "Myanmar civil war — junta vs resistance forces",
      "id": "known-8",
      "timestamp": "2026-07-18T23:15:55.398Z"
    },
    {
      "type": "military_mobilisation",
      "country": "ETH",
      "target": "ERI",
      "severity": "high",
      "headline": "Ethiopia–Eritrea border tensions persist",
      "id": "known-9",
      "timestamp": "2026-07-18T23:15:55.398Z"
    },
    {
      "type": "military_mobilisation",
      "country": "SOM",
      "target": "ETH",
      "severity": "high",
      "headline": "Somalia–Ethiopia tensions over Somaliland port deal",
      "id": "known-10",
      "timestamp": "2026-07-18T23:15:55.398Z"
    },
    {
      "type": "military_mobilisation",
      "country": "COD",
      "target": "RWA",
      "severity": "high",
      "headline": "DR Congo–Rwanda conflict over M23 militia in eastern DRC",
      "id": "known-11",
      "timestamp": "2026-07-18T23:15:55.398Z"
    },
    {
      "type": "military_mobilisation",
      "country": "PAK",
      "target": "AFG",
      "severity": "medium",
      "headline": "Pakistan–Afghanistan cross-border military operations",
      "id": "known-12",
      "timestamp": "2026-07-18T23:15:55.398Z"
    },
    {
      "type": "military_mobilisation",
      "country": "CHN",
      "target": "TWN",
      "severity": "high",
      "headline": "China–Taiwan strait military posturing",
      "id": "known-13",
      "timestamp": "2026-07-18T23:15:55.398Z"
    },
    {
      "type": "military_mobilisation",
      "country": "CHN",
      "target": "PHL",
      "severity": "medium",
      "headline": "China–Philippines South China Sea territorial disputes",
      "id": "known-14",
      "timestamp": "2026-07-18T23:15:55.398Z"
    },
    {
      "type": "military_mobilisation",
      "country": "PRK",
      "target": "KOR",
      "severity": "medium",
      "headline": "North Korea–South Korea military standoff",
      "id": "known-15",
      "timestamp": "2026-07-18T23:15:55.398Z"
    },
    {
      "type": "military_mobilisation",
      "country": "IND",
      "target": "PAK",
      "severity": "medium",
      "headline": "India–Pakistan border tensions in Kashmir",
      "id": "known-16",
      "timestamp": "2026-07-18T23:15:55.398Z"
    },
    {
      "type": "military_mobilisation",
      "country": "RUS",
      "target": "GEO",
      "severity": "medium",
      "headline": "Russia–Georgia tensions over occupied territories",
      "id": "known-17",
      "timestamp": "2026-07-18T23:15:55.398Z"
    },
    {
      "type": "trade",
      "country": "CHN",
      "target": "USA",
      "severity": "medium",
      "headline": "US–China trade war and tariff escalation",
      "id": "known-18",
      "timestamp": "2026-07-18T23:15:55.398Z"
    },
    {
      "type": "trade",
      "country": "USA",
      "target": "RUS",
      "severity": "medium",
      "headline": "US-led economic sanctions on Russia",
      "id": "known-19",
      "timestamp": "2026-07-18T23:15:55.398Z"
    },
    {
      "type": "trade",
      "country": "DEU",
      "target": "NOR",
      "severity": "low",
      "headline": "Germany–Norway energy corridor partnership",
      "id": "known-20",
      "timestamp": "2026-07-18T23:15:55.398Z"
    },
    {
      "type": "trade",
      "country": "JPN",
      "target": "USA",
      "severity": "low",
      "headline": "Japan–US semiconductor supply chain agreement",
      "id": "known-21",
      "timestamp": "2026-07-18T23:15:55.398Z"
    },
    {
      "type": "trade",
      "country": "IND",
      "target": "RUS",
      "severity": "medium",
      "headline": "India–Russia oil and energy trade partnership",
      "id": "known-22",
      "timestamp": "2026-07-18T23:15:55.398Z"
    },
    {
      "type": "trade",
      "country": "AUS",
      "target": "CHN",
      "severity": "medium",
      "headline": "Australia–China trade disputes over critical minerals",
      "id": "known-23",
      "timestamp": "2026-07-18T23:15:55.398Z"
    },
    {
      "type": "trade",
      "country": "GBR",
      "target": "FRA",
      "severity": "low",
      "headline": "UK–EU post-Brexit trade friction",
      "id": "known-24",
      "timestamp": "2026-07-18T23:15:55.398Z"
    },
    {
      "type": "trade",
      "country": "KOR",
      "target": "JPN",
      "severity": "low",
      "headline": "South Korea–Japan semiconductor export controls",
      "id": "known-25",
      "timestamp": "2026-07-18T23:15:55.398Z"
    },
    {
      "type": "trade",
      "country": "BRA",
      "target": "CHN",
      "severity": "low",
      "headline": "Brazil–China commodity export corridor",
      "id": "known-26",
      "timestamp": "2026-07-18T23:15:55.398Z"
    },
    {
      "type": "trade",
      "country": "SAU",
      "target": "IND",
      "severity": "low",
      "headline": "Saudi Arabia–India oil supply agreement",
      "id": "known-27",
      "timestamp": "2026-07-18T23:15:55.398Z"
    },
    {
      "type": "trade",
      "country": "TUR",
      "target": "RUS",
      "severity": "medium",
      "headline": "Turkey–Russia energy and trade corridor",
      "id": "known-28",
      "timestamp": "2026-07-18T23:15:55.398Z"
    }
  ]
}