{
  "updated": "2026-03-11T05:07:03.938Z",
  "count": 35,
  "events": [
    {
      "id": "117374103320e5b43325dab8405d9a3b",
      "type": "military_mobilisation",
      "headline": "A murderous thug has dirt on Trump. Nothing else explains this madness",
      "country": "USA",
      "target": "RUS",
      "timestamp": "2026-03-10 17:06:49",
      "severity": "critical"
    },
    {
      "id": "1aa17cad59d5726c6b37e116240c4190",
      "type": "leadership_change",
      "headline": "Macron's G7 Call: Navigating the Oil Crisis Amidst Middle East Tensions",
      "country": "IND",
      "target": "ISR",
      "timestamp": "2026-03-10 17:06:48",
      "severity": "high"
    },
    {
      "id": "bbd7498c1a0832e3c37f9be9540645ba",
      "type": "military_mobilisation",
      "headline": "Lavrov, Araghchi hold call as Iran rejects ceasefire demands, US terms Russia-Iran ties 'symbiotic'",
      "country": "IND",
      "target": "RUS",
      "timestamp": "2026-03-10 17:06:46",
      "severity": "high"
    },
    {
      "id": "d67301057163d98646dfa586a03f0dc9",
      "type": "diplomacy",
      "headline": "British Airways stopping flights to war torn Middle East country until later this year",
      "country": "GBR",
      "target": null,
      "timestamp": "2026-03-10 17:06:40",
      "severity": "critical"
    },
    {
      "id": "7585f972072acc7d2586608ab83a83ff",
      "type": "diplomacy",
      "headline": "U.S. Proposed Ukraine-Russia Talks Next Week – Zelensky",
      "country": "RUS",
      "target": "UKR",
      "timestamp": "2026-03-10 17:06:20",
      "severity": "low"
    },
    {
      "id": "3d583635519fd83bcefa9ef77dcd4567",
      "type": "diplomacy",
      "headline": "Meet the embattled French WW2 leader who withstood the Nazis – and Winston Churchill",
      "country": "GBR",
      "target": "FRA",
      "timestamp": "2026-03-10 17:06:00",
      "severity": "medium"
    },
    {
      "id": "9f418f049e70c3f82e10f70cf8d6cda1",
      "type": "leadership_change",
      "headline": "Kalamazoo Township official calls for treasurer’s resignation",
      "country": "USA",
      "target": null,
      "timestamp": "2026-03-10 17:05:55",
      "severity": "medium"
    },
    {
      "id": "6362bc2c85a7b301a7d7368774938d13",
      "type": "trade",
      "headline": "EXPLAINER | Challenges in securing shipping through the Strait of Hormuz",
      "country": "ZAF",
      "target": null,
      "timestamp": "2026-03-10 17:05:48",
      "severity": "critical"
    },
    {
      "id": "e79e51d25e6eef8a6706ac483ac80e6c",
      "type": "leadership_change",
      "headline": "Primate Ayodele prophesies Donald Trump will remove African presidents, flags danger to Tinubu",
      "country": "NGA",
      "target": "USA",
      "timestamp": "2026-03-10 17:05:41",
      "severity": "critical"
    },
    {
      "type": "military_mobilisation",
      "country": "ISR",
      "target": "PSE",
      "severity": "critical",
      "headline": "Israel–Palestine military operations in Gaza",
      "id": "known-0",
      "timestamp": "2026-03-11T05:07:03.937Z"
    },
    {
      "type": "military_mobilisation",
      "country": "ISR",
      "target": "LBN",
      "severity": "high",
      "headline": "Israel–Hezbollah cross-border conflict in Lebanon",
      "id": "known-1",
      "timestamp": "2026-03-11T05:07:03.937Z"
    },
    {
      "type": "military_mobilisation",
      "country": "ISR",
      "target": "SYR",
      "severity": "high",
      "headline": "Israeli military strikes on targets in Syria",
      "id": "known-2",
      "timestamp": "2026-03-11T05:07:03.937Z"
    },
    {
      "type": "military_mobilisation",
      "country": "ISR",
      "target": "YEM",
      "severity": "high",
      "headline": "Israel–Houthi exchange of strikes via Yemen",
      "id": "known-3",
      "timestamp": "2026-03-11T05:07:03.937Z"
    },
    {
      "type": "military_mobilisation",
      "country": "IRN",
      "target": "ISR",
      "severity": "high",
      "headline": "Iran–Israel strategic military confrontation",
      "id": "known-4",
      "timestamp": "2026-03-11T05:07:03.937Z"
    },
    {
      "type": "military_mobilisation",
      "country": "USA",
      "target": "IRN",
      "severity": "high",
      "headline": "US military operations and sanctions against Iran",
      "id": "known-5",
      "timestamp": "2026-03-11T05:07:03.937Z"
    },
    {
      "type": "military_mobilisation",
      "country": "USA",
      "target": "YEM",
      "severity": "high",
      "headline": "US airstrikes on Houthi positions in Yemen",
      "id": "known-6",
      "timestamp": "2026-03-11T05:07:03.937Z"
    },
    {
      "type": "invasion",
      "country": "SDN",
      "target": "SSD",
      "severity": "critical",
      "headline": "Sudan civil war — RSF vs SAF armed conflict",
      "id": "known-7",
      "timestamp": "2026-03-11T05:07:03.937Z"
    },
    {
      "type": "invasion",
      "country": "MMR",
      "target": "MMR",
      "severity": "critical",
      "headline": "Myanmar civil war — junta vs resistance forces",
      "id": "known-8",
      "timestamp": "2026-03-11T05:07:03.937Z"
    },
    {
      "type": "military_mobilisation",
      "country": "ETH",
      "target": "ERI",
      "severity": "high",
      "headline": "Ethiopia–Eritrea border tensions persist",
      "id": "known-9",
      "timestamp": "2026-03-11T05:07:03.937Z"
    },
    {
      "type": "military_mobilisation",
      "country": "SOM",
      "target": "ETH",
      "severity": "high",
      "headline": "Somalia–Ethiopia tensions over Somaliland port deal",
      "id": "known-10",
      "timestamp": "2026-03-11T05:07:03.937Z"
    },
    {
      "type": "military_mobilisation",
      "country": "COD",
      "target": "RWA",
      "severity": "high",
      "headline": "DR Congo–Rwanda conflict over M23 militia in eastern DRC",
      "id": "known-11",
      "timestamp": "2026-03-11T05:07:03.937Z"
    },
    {
      "type": "military_mobilisation",
      "country": "PAK",
      "target": "AFG",
      "severity": "medium",
      "headline": "Pakistan–Afghanistan cross-border military operations",
      "id": "known-12",
      "timestamp": "2026-03-11T05:07:03.937Z"
    },
    {
      "type": "military_mobilisation",
      "country": "CHN",
      "target": "TWN",
      "severity": "high",
      "headline": "China–Taiwan strait military posturing",
      "id": "known-13",
      "timestamp": "2026-03-11T05:07:03.937Z"
    },
    {
      "type": "military_mobilisation",
      "country": "CHN",
      "target": "PHL",
      "severity": "medium",
      "headline": "China–Philippines South China Sea territorial disputes",
      "id": "known-14",
      "timestamp": "2026-03-11T05:07:03.937Z"
    },
    {
      "type": "military_mobilisation",
      "country": "PRK",
      "target": "KOR",
      "severity": "medium",
      "headline": "North Korea–South Korea military standoff",
      "id": "known-15",
      "timestamp": "2026-03-11T05:07:03.937Z"
    },
    {
      "type": "military_mobilisation",
      "country": "IND",
      "target": "PAK",
      "severity": "medium",
      "headline": "India–Pakistan border tensions in Kashmir",
      "id": "known-16",
      "timestamp": "2026-03-11T05:07:03.937Z"
    },
    {
      "type": "military_mobilisation",
      "country": "RUS",
      "target": "GEO",
      "severity": "medium",
      "headline": "Russia–Georgia tensions over occupied territories",
      "id": "known-17",
      "timestamp": "2026-03-11T05:07:03.937Z"
    },
    {
      "type": "trade",
      "country": "CHN",
      "target": "USA",
      "severity": "medium",
      "headline": "US–China trade war and tariff escalation",
      "id": "known-18",
      "timestamp": "2026-03-11T05:07:03.937Z"
    },
    {
      "type": "trade",
      "country": "DEU",
      "target": "NOR",
      "severity": "low",
      "headline": "Germany–Norway energy corridor partnership",
      "id": "known-19",
      "timestamp": "2026-03-11T05:07:03.937Z"
    },
    {
      "type": "trade",
      "country": "JPN",
      "target": "USA",
      "severity": "low",
      "headline": "Japan–US semiconductor supply chain agreement",
      "id": "known-20",
      "timestamp": "2026-03-11T05:07:03.937Z"
    },
    {
      "type": "trade",
      "country": "AUS",
      "target": "CHN",
      "severity": "medium",
      "headline": "Australia–China trade disputes over critical minerals",
      "id": "known-21",
      "timestamp": "2026-03-11T05:07:03.937Z"
    },
    {
      "type": "trade",
      "country": "KOR",
      "target": "JPN",
      "severity": "low",
      "headline": "South Korea–Japan semiconductor export controls",
      "id": "known-22",
      "timestamp": "2026-03-11T05:07:03.937Z"
    },
    {
      "type": "trade",
      "country": "BRA",
      "target": "CHN",
      "severity": "low",
      "headline": "Brazil–China commodity export corridor",
      "id": "known-23",
      "timestamp": "2026-03-11T05:07:03.937Z"
    },
    {
      "type": "trade",
      "country": "SAU",
      "target": "IND",
      "severity": "low",
      "headline": "Saudi Arabia–India oil supply agreement",
      "id": "known-24",
      "timestamp": "2026-03-11T05:07:03.937Z"
    },
    {
      "type": "trade",
      "country": "TUR",
      "target": "RUS",
      "severity": "medium",
      "headline": "Turkey–Russia energy and trade corridor",
      "id": "known-25",
      "timestamp": "2026-03-11T05:07:03.937Z"
    }
  ]
}